logorator/__init__.py
logorator/logger.py
logorator-1.0.7.dist-info/METADATA
logorator-1.0.7.dist-info/WHEEL
logorator-1.0.7.dist-info/top_level.txt
logorator-1.0.7.dist-info/RECORD
