Metadata-Version: 2.2
Name: logorator
Version: 1.0.7
Summary: A decorator-based logging library with hierarchical structure, ANSI color support, and configurable outputs.
Author-email: Arved Klöhn <arved.kloehn@gmail.com>
Keywords: logging,decorator,hierarchical logging
Classifier: Development Status :: 5 - Production/Stable
Classifier: Intended Audience :: Developers
Classifier: License :: OSI Approved :: MIT License
Classifier: Programming Language :: Python
Classifier: Programming Language :: Python :: 3
Classifier: Programming Language :: Python :: 3.7
Classifier: Programming Language :: Python :: 3.8
Classifier: Programming Language :: Python :: 3.9
Classifier: Programming Language :: Python :: 3.10
Classifier: Programming Language :: Python :: 3.11
Classifier: Topic :: Software Development :: Libraries
Classifier: Topic :: Utilities
